{"language": "english", "text": {"0": {"0": {}, "1": {}, "2": {}, "3": {}, "4": {"0": "", "1": "", "2": "<b>if it has in its circumference:</b> Which is to say, what is the the round measurement required to render [the beam] proper? Anything that has in its circumference three handbreadths, which requires a string of three handbreadths to encircle it around, it is known that it has a width (diameter) of one handbreadth, if you divide [it]. As so do we find with the basin that Shlomo made (II Chronicles 4:2), \"ten ells from its edge to its edge and five ells of height and a line of thirty ells encircling it around.\" Hence for every ell in width (diameter), there are three ells in circumference.\n"}}}, "originalTitle": "\u05d1\u05e8\u05d8\u05e0\u05d5\u05e8\u05d0 \u05e2\u05dc \u05de\u05e9\u05e0\u05d4 \u05e2\u05d9\u05e8\u05d5\u05d1\u05d9\u05df", "source": "Sefaria", "englishTitle": "Bartenura on Mishnah Eruvin", "author": "Not available", "sourceLink": "http://www.sefaria.org/"}