{"originalTitle": "\u05de\u05e6\u05d5\u05d3\u05ea \u05d3\u05d5\u05d3 \u05e2\u05dc \u05d9\u05e8\u05de\u05d9\u05d4\u05d5", "sourceLink": "http://www.sefaria.org/", "language": "english", "author": "Not available", "englishTitle": "Metzudat David on Jeremiah", "source": "Sefaria", "text": {"0": {"0": "For there is a day \u2013 There is a day prepared on which the scouts who stand on the mountains will call aloud \u2018Rise! Let us go up to Zion, to the Lord\u2019 because the redemption has come and the Divine Presence returned to her place in Zion:"}, "1": {"0": {"0": "and this is the name that He shall call it \u2013 This is the name which God will call Jerusalem: ", "1": "the Lord is our righteousness \u2013 God will make us righteous when she (Jerusalem) is reestablished."}}}}